Metadata-Version: 1.0
Name: ratatosk
Version: 0.1.0
Summary: Project/pipeline manager
Home-page: UNKNOWN
Author: Per Unneberg
Author-email: per.unneberg@scilifelab.se
License: Apache
Platform: UNKNOWN
